auto34diff/__init__.py
auto34diff/autodiff.py
auto34diff/forward.py
auto34diff/functions.py
auto34diff/reverse.py
auto34diff-0.1.3.dist-info/LICENSE
auto34diff-0.1.3.dist-info/METADATA
auto34diff-0.1.3.dist-info/WHEEL
auto34diff-0.1.3.dist-info/top_level.txt
auto34diff-0.1.3.dist-info/RECORD
