Metadata-Version: 2.1
Name: auto34diff
Version: 0.1.3
Summary: CS107 team34 autodiff package
Author: CS107/team34
License: MIT
License-File: LICENSE
Requires-Dist: numpy
